hana_ml/__init__.py
hana_ml/dataframe.py
hana_ml/dataset_manager.py
hana_ml/hana_scheduler.py
hana_ml/ml_base.py
hana_ml/ml_exceptions.py
hana_ml/model_storage.py
hana_ml/model_storage_services.py
hana_ml/type_codes.py
hana_ml/algorithms/__init__.py
hana_ml/algorithms/apl/__init__.py
hana_ml/algorithms/apl/apl_artifact.py
hana_ml/algorithms/apl/apl_base.py
hana_ml/algorithms/apl/artifacts_recorder.py
hana_ml/algorithms/apl/classification.py
hana_ml/algorithms/apl/clustering.py
hana_ml/algorithms/apl/drift_detector.py
hana_ml/algorithms/apl/gradient_boosting_base.py
hana_ml/algorithms/apl/gradient_boosting_classification.py
hana_ml/algorithms/apl/gradient_boosting_regression.py
hana_ml/algorithms/apl/regression.py
hana_ml/algorithms/apl/robust_regression_base.py
hana_ml/algorithms/apl/sqlgen.py
hana_ml/algorithms/apl/time_series.py
hana_ml/algorithms/pal/__init__.py
hana_ml/algorithms/pal/abc_analysis.py
hana_ml/algorithms/pal/association.py
hana_ml/algorithms/pal/auto_ml.py
hana_ml/algorithms/pal/clustering.py
hana_ml/algorithms/pal/crf.py
hana_ml/algorithms/pal/dataset_cards.py
hana_ml/algorithms/pal/decomposition.py
hana_ml/algorithms/pal/discriminant_analysis.py
hana_ml/algorithms/pal/fair_ml.py
hana_ml/algorithms/pal/feature_tool.py
hana_ml/algorithms/pal/kernel_density.py
hana_ml/algorithms/pal/linear_model.py
hana_ml/algorithms/pal/linkpred.py
hana_ml/algorithms/pal/massive_auto_ml.py
hana_ml/algorithms/pal/metrics.py
hana_ml/algorithms/pal/mixture.py
hana_ml/algorithms/pal/model_cards.py
hana_ml/algorithms/pal/model_selection.py
hana_ml/algorithms/pal/naive_bayes.py
hana_ml/algorithms/pal/neighbors.py
hana_ml/algorithms/pal/neural_network.py
hana_ml/algorithms/pal/outlier_profiling.py
hana_ml/algorithms/pal/pagerank.py
hana_ml/algorithms/pal/pal_base.py
hana_ml/algorithms/pal/partition.py
hana_ml/algorithms/pal/pipeline.py
hana_ml/algorithms/pal/preprocessing.py
hana_ml/algorithms/pal/random.py
hana_ml/algorithms/pal/recommender.py
hana_ml-2.27.26012900.dist-info/LICENSE
hana_ml-2.27.26012900.dist-info/METADATA
hana_ml-2.27.26012900.dist-info/WHEEL
hana_ml-2.27.26012900.dist-info/top_level.txt
hana_ml-2.27.26012900.dist-info/RECORD
