Metadata-Version: 2.1
Name: hana-ml
Version: 2.27.26012900
Summary: Python Machine Learning Client for SAP HANA
Home-page: https://www.sap.com/
Author: SAP SE
License: SAP DEVELOPER LICENSE AGREEMENT
Project-URL: Documentation, https://help.sap.com/doc/cd94b08fe2e041c2ba778374572ddba9/latest/en-US/hana_ml.html
Project-URL: Report Issues, https://github.com/SAP-samples/hana-ml-samples/issues
Project-URL: Notebook Examples, https://github.com/SAP-samples/hana-ml-samples/tree/main/Python-API/pal/notebooks
Keywords: SAP HANA machine learning intelligent enterprise cloud PAL APL client
Platform: UNKNOWN
Classifier: Programming Language :: Python :: 3.4
Classifier: Programming Language :: Python :: 3.5
Classifier: Programming Language :: Python :: 3.6
Classifier: Programming Language :: Python :: 3.7
Classifier: Programming Language :: Python :: 3.8
Classifier: Programming Language :: Python :: 3.9
Classifier: Programming Language :: Python :: 3.10
Classifier: Programming Language :: Python :: 3.11
Classifier: Programming Language :: Python :: 3.12
Classifier: Development Status :: 5 - Production/Stable
Classifier: Intended Audience :: Developers
Classifier: Intended Audience :: Science/Research
Classifier: Operating System :: Microsoft
Classifier: Operating System :: Other OS
Requires-Python: >=3.4
Requires-Dist: hdbcli (>=2.18.22)
Requires-Dist: pydotplus
Requires-Dist: Deprecated
Requires-Dist: tqdm (>=4.43.0)
Requires-Dist: schedule
Requires-Dist: prettytable
Requires-Dist: shapely (>=1.8.1)
Requires-Dist: plotly (>=4.14.3)
Requires-Dist: numpy (<1.16.4) ; python_version < "3.4"
Requires-Dist: pandas (<0.24.2) ; python_version < "3.4"
Requires-Dist: numpy (>=1.16.4) ; python_version >= "3.4"
Requires-Dist: pandas (<3,>=0.24) ; python_version >= "3.4"
Requires-Dist: jinja2 (>=3.0.0) ; python_version >= "3.4"
